sklearn_ml/__init__.py
sklearn_ml/_core.py
sklearn_ml-2.2.dist-info/METADATA
sklearn_ml-2.2.dist-info/WHEEL
sklearn_ml-2.2.dist-info/top_level.txt
sklearn_ml-2.2.dist-info/RECORD
