Metadata-Version: 2.1
Name: sklearn_ml
Version: 2.2
Summary: A light package build on scikit-learn, which is used for machine learning missions.By using it, you could conveniently train and use models at the same time, and do some model comparison.
Home-page: https://github.com/ChaneMo/sklearn-ml
Author: ChaneMo
Author-email: 
License: Apache 2.0
Keywords: scikit-learn,sklearn,classification,regression,cluster,machine learning,model comparison
Classifier: Development Status :: 3 - Alpha
Classifier: Intended Audience :: Developers
Classifier: Programming Language :: Python :: 3
Classifier: Programming Language :: Python :: 3.7
Classifier: Programming Language :: Python :: 3.8
Classifier: Programming Language :: Python :: 3.9
Classifier: Programming Language :: Python :: 3.10
Classifier: Programming Language :: Python :: 3 :: Only
Classifier: License :: OSI Approved :: MIT License
Classifier: Operating System :: OS Independent
Requires-Python: >=3.6
Requires-Dist: pandas
Requires-Dist: scikit-learn
